[
    {
        "text": "Hello",
        "author": "Jeevan"
    },
    {
        "text": "No problem",
        "author": "Biri Singh"
    },
    {
        "text": "hello",
        "author": "Biri Singh"
    },
    {
        "text": "Hi",
        "author": "naveen"
    },
    {
        "text": "Hello Everytone",
        "author": "Shintu singh"
    },
    {
        "text": "Hello",
        "author": "Ravi"
    },
    {
        "text": "Hi",
        "author": "parveen"
    },
    {
        "text": "Lunch karne chalen ?",
        "author": "Naveen"
    }
]